jk_flipflop.v
module jk_flipflop(q,q1,j,k,c);
output q,q1;
input j,k,c;
reg q,q1;
initial begin q=1'b0; q1=1'b1; end
always @ (posedge c)
  begin
	case({j,k})
		 {1'b0,1'b0}:begin q=q; q1=q1; end
		 {1'b0,1'b1}: begin q=1'b0; q1=1'b1; end
		 {1'b1,1'b0}:begin q=1'b1; q1=1'b0; end
		 {1'b1,1'b1}: begin q=~q; q1=~q1; end
	endcase
   end
endmodule

jk_flipflop_tb.v
module jk_flipfloptb;
reg j,k,clock;
wire q,q1;

jk_flipflop jkff(.q(q),
.q1(q1),
.j(j),
.k(k),
.c(clock)
);

initial begin
  clock = 1;
  j=0;
  k=0;
  #100;
  #5 $finish;
end

always begin
#5 clock = ~clock;
#5 j = ~j;
#10 k = ~k;
end

initial begin
   $dumpfile("jk_flipfloptb.vcd");
   $dumpvars(0,jk_flipfloptb);
   $display("time\t clock\t j\t k\t q\t q1\t");
   $monitor("%g\t %b\t %b\t %b\t %b\t %b\t",$time,clock, j, k, q, q1);
end
endmodule

jk_flipfloptb.vcd
$date
	Thu Oct 11 15:42:58 2018
$end
$version
	Icarus Verilog
$end
$timescale
	1s
$end
$scope module jk_flipfloptb $end
$var wire 1 ! q $end
$var wire 1 " q1 $end
$var reg 1 # clock $end
$var reg 1 $ j $end
$var reg 1 % k $end
$scope module jkff $end
$var wire 1 & c $end
$var wire 1 ' j $end
$var wire 1 ( k $end
$var reg 1 ) q $end
$var reg 1 * q1 $end
$upscope $end
$upscope $end
$enddefinitions $end
#0
$dumpvars
1*
0)
0(
0'
1&
0%
0$
1#
1"
0!
$end
#5
0#
0&
#10
1$
1'
#20
1%
1(
#25
0*
0"
1)
1!
1#
1&
#30
0$
0'
#40
0%
0(
#45
0#
0&
#50
1$
1'
#60
1%
1(
#65
1*
1"
0)
0!
1#
1&
#70
0$
0'
#80
0%
0(
#85
0#
0&
#90
1$
1'
#100
1%
1(
#105
0*
0"
1)
1!
1#
1&
