sr_flipflop.v
module sr_flipflop(q, q1, r, s, clk);

output q,q1;
input r,s,clk;
reg q,q1;
initial begin
  q = 1'b0;
  q1 = 1'b1;
end
always @ ( posedge clk ) begin
  case({s,r})
    {1'b0,1'b0}: begin q =q; q1=q1; end
    {1'b0,1'b1}: begin q =1'b0; q1 = 1'b1; end
    {1'b1,1'b0}: begin q=1'b1; q1 = 1'b0; end
    {1'b1,1'b1}: begin q=1'bx; q=1'bx; end
    endcase
end

endmodule

sr_flipflop_tb.v
module sr_flipfloptb;
reg r,s,clock;
wire q,q1;

sr_flipflop srff(.q(q),
.q1(q1),
.r(r),
.s(s),
.clk(clock)
);

initial begin
  clock = 1;
  r=0;
  s=0;
  #100;
  #5 $finish;
end

always begin
#5 clock = ~clock;
#5 s = ~s;
end

initial begin
   $dumpfile("sr_flipfloptb.vcd");
   $dumpvars(0,sr_flipfloptb);
   $display("time\t clock\t r\t s\t q\t q1\t");
   $monitor("%g\t %b\t %b\t %b\t %b\t %b\t",$time,clock, r, s, q, q1);
end
endmodule

sr_flipfloptb.vcd
$date
	Thu Oct 11 15:34:52 2018
$end
$version
	Icarus Verilog
$end
$timescale
	1s
$end
$scope module sr_flipfloptb $end
$var wire 1 ! q $end
$var wire 1 " q1 $end
$var reg 1 # clock $end
$var reg 1 $ r $end
$var reg 1 % s $end
$scope module srff $end
$var wire 1 & clk $end
$var wire 1 ' r $end
$var wire 1 ( s $end
$var reg 1 ) q $end
$var reg 1 * q1 $end
$upscope $end
$upscope $end
$enddefinitions $end
#0
$dumpvars
1*
0)
0(
0'
1&
0%
0$
1#
1"
0!
$end
#5
0#
0&
#10
1%
1(
#15
0*
0"
1)
1!
1#
1&
#20
0%
0(
#25
0#
0&
#30
1%
1(
#35
1#
1&
#40
0%
0(
#45
0#
0&
#50
1%
1(
#55
1#
1&
#60
0%
0(
#65
0#
0&
#70
1%
1(
#75
1#
1&
#80
0%
0(
#85
0#
0&
#90
1%
1(
#95
1#
1&
#100
0%
0(
